modal_server/__init__.py
modal_server/server.py
mseep_modal_server-0.1.3.dist-info/METADATA
mseep_modal_server-0.1.3.dist-info/WHEEL
mseep_modal_server-0.1.3.dist-info/entry_points.txt
mseep_modal_server-0.1.3.dist-info/top_level.txt
mseep_modal_server-0.1.3.dist-info/RECORD
